[{"address":"0x00000000eFE302BEAA2b3e6e1b18d08D69a9012a","name":"AUSD","symbol":"AUSD","decimals":6,"addedAt":1750793953,"mcap":171125653},{"address":"0x876aac7648D79f87245E73316eB2D100e75F3Df1","name":"BitVault USD","symbol":"bvUSD","decimals":18,"addedAt":1783611729},{"address":"0x7F1f4b4b29f5058fA32CC7a97141b8D7e5ABDC2d","name":"Katana Network Token","symbol":"KAT","decimals":18,"addedAt":1783611729,"mcap":13446820},{"address":"0x17BFF452dae47e07CeA877Ff0E1aba17eB62b0aB","name":"SushiToken","symbol":"SUSHI","decimals":18,"addedAt":1783611729,"mcap":45242667},{"address":"0x83f31af747189c2FA9E5DeB253200c505eff6ed2","name":"ZCash (Universal)","symbol":"uZEC","decimals":18,"mcap":8463211350},{"address":"0xEE7D8BCFb72bC1880D0Cf19822eB0A2e6577aB62","name":"Vault Bridge ETH","symbol":"vbETH","decimals":18,"addedAt":1751033104,"mcap":14061270},{"address":"0x203A662b0BD271A6ed5a60EdFbd04bFce608FD36","name":"Vault Bridge USDC","symbol":"vbUSDC","decimals":6,"addedAt":1751033104,"mcap":16789890},{"address":"0x62D6A123E8D19d06d68cf0d2294F9A3A0362c6b3","name":"Vault Bridge USDS","symbol":"vbUSDS","decimals":18,"addedAt":1751033104,"mcap":10896002231},{"address":"0x2DCa96907fde857dd3D816880A0df407eeB2D2F2","name":"Vault Bridge USDT","symbol":"vbUSDT","decimals":6,"addedAt":1751033104,"mcap":5605760},{"address":"0x0913DA6Da4b42f538B445599b46Bb4622342Cf52","name":"Vault Bridge WBTC","symbol":"vbWBTC","decimals":8,"addedAt":1751033104,"mcap":20866725},{"address":"0xE007CA01894c863d7898045ed5A3B4Abf0b18f37","name":"vbETH yVault","symbol":"yvvbETH","decimals":18,"addedAt":1751033104},{"address":"0x80c34BD3A3569E126e7055831036aa7b212cB159","name":"vbUSDC yVault","symbol":"yvvbUSDC","decimals":6,"addedAt":1751033104},{"address":"0x8Fb1c10Ad4417EcA341a1D903Ff437d25ff87a4e","name":"vbUSDS yVault","symbol":"yvvbUSDS","decimals":18,"addedAt":1751033104},{"address":"0x9A6bd7B6Fd5C4F87eb66356441502fc7dCdd185B","name":"vbUSDT yVault","symbol":"yvvbUSDT","decimals":6,"addedAt":1751033104},{"address":"0xAa0362eCC584B985056E47812931270b99C91f9d","name":"vbWBTC yVault","symbol":"yvvbWBTC","decimals":8,"addedAt":1751033104}]